flirextractor/__init__.py
flirextractor/__version__.py
flirextractor/flirextractor.py
flirextractor/get_thermal.py
flirextractor/pathutils.py
flirextractor/py.typed
flirextractor/raw_temp_to_celcius.py
flirextractor/utils.py
flirextractor-1.0.2.dist-info/LICENSE.md
flirextractor-1.0.2.dist-info/WHEEL
flirextractor-1.0.2.dist-info/METADATA
flirextractor-1.0.2.dist-info/RECORD
