Metadata-Version: 2.1
Name: flirextractor
Version: 1.0.2
Summary: An efficient GPLv3-licensed Python package for extracting temperature data from FLIR IRT images.
Home-page: https://github.com/aloisklink/flirextractor
License: GPL-3.0+
Author: Alois Klink
Author-email: alois.klink@gmail.com
Requires-Python: >=3.6,<4.0
Classifier: Intended Audience :: Science/Research
Classifier: License :: OSI Approved :: GNU General Public License v3 or later (GPLv3+)
Classifier: Programming Language :: Python :: 3
Classifier: Programming Language :: Python :: 3.6
Classifier: Programming Language :: Python :: 3.7
Classifier: Programming Language :: Python :: 3.8
Classifier: Topic :: Multimedia :: Graphics :: Capture :: Digital Camera
Requires-Dist: numpy (>=1.17,<2.0)
Requires-Dist: pillow (>=6.2,<=8.0.0)
Requires-Dist: pyexiftool (>=0.1.1,<0.2.0)
Project-URL: Repository, https://github.com/aloisklink/flirextractor
